{"Version":"5.17.18.1","ElectionId":"2024 General Election","Sessions":[{"TabulatorId":939908,"BatchId":1,"RecordId":4805401,"CountingGroupId":1,"ImageMask":"D:\\NAS\\2024 General Election\\Results\\Tabulator939908\\Batch001\\Images\\939908_00001_4805401*.*","SessionType":"DreVote","VotingSessionIdentifier":"939908_d52d18e3-f9b6-41b2-9022-151b2180f2e6","UniqueVotingIdentifier":"995_536868e0-5f70-4740-aa52-00b61cba26b3","Original":{"PrecinctPortionId":357,"BallotTypeId":44,"IsCurrent":true,"Cards":[{"Id":1066,"KeyInId":1066,"PaperIndex":0,"Contests":[{"Id":4,"ManifestationId":896,"Undervotes":0,"Overvotes":0,"OutstackConditionIds":[14],"Marks":[{"CandidateId":543,"ManifestationId":7368,"PartyId":15,"Rank":1,"MarkDensity":100,"IsAmbiguous":false,"IsVote":true,"OutstackConditionIds":[]}]},{"Id":7,"ManifestationId":897,"Undervotes":0,"Overvotes":0,"OutstackConditionIds":[14],"Marks":[{"CandidateId":517,"ManifestationId":7434,"PartyId":15,"Rank":1,"MarkDensity":100,"IsAmbiguous":false,"IsVote":true,"OutstackConditionIds":[]}]},{"Id":27,"ManifestationId":898,"Undervotes":0,"Overvotes":0,"OutstackConditionIds":[14],"Marks":[{"CandidateId":379,"ManifestationId":7457,"PartyId":7,"Rank":1,"MarkDensity":100,"IsAmbiguous":false,"IsVote":true,"OutstackConditionIds":[]}]},{"Id":66,"ManifestationId":899,"Undervotes":0,"Overvotes":0,"OutstackConditionIds":[14],"Marks":[{"CandidateId":462,"ManifestationId":7462,"PartyId":7,"Rank":1,"MarkDensity":100,"IsAmbiguous":false,"IsVote":true,"OutstackConditionIds":[]}]},{"Id":68,"ManifestationId":900,"Undervotes":0,"Overvotes":0,"OutstackConditionIds":[],"Marks":[{"CandidateId":218,"ManifestationId":7471,"PartyId":0,"Rank":1,"MarkDensity":100,"IsAmbiguous":false,"IsVote":true,"OutstackConditionIds":[]}]},{"Id":69,"ManifestationId":901,"Undervotes":0,"Overvotes":0,"OutstackConditionIds":[],"Marks":[{"CandidateId":220,"ManifestationId":7473,"PartyId":0,"Rank":1,"MarkDensity":100,"IsAmbiguous":false,"IsVote":true,"OutstackConditionIds":[]}]},{"Id":71,"ManifestationId":902,"Undervotes":0,"Overvotes":0,"OutstackConditionIds":[],"Marks":[{"CandidateId":224,"ManifestationId":7475,"PartyId":0,"Rank":1,"MarkDensity":100,"IsAmbiguous":false,"IsVote":true,"OutstackConditionIds":[]}]},{"Id":72,"ManifestationId":903,"Undervotes":0,"Overvotes":0,"OutstackConditionIds":[],"Marks":[{"CandidateId":226,"ManifestationId":7477,"PartyId":0,"Rank":1,"MarkDensity":100,"IsAmbiguous":false,"IsVote":true,"OutstackConditionIds":[]}]},{"Id":76,"ManifestationId":904,"Undervotes":0,"Overvotes":0,"OutstackConditionIds":[],"Marks":[{"CandidateId":234,"ManifestationId":7479,"PartyId":0,"Rank":1,"MarkDensity":100,"IsAmbiguous":false,"IsVote":true,"OutstackConditionIds":[]}]},{"Id":77,"ManifestationId":905,"Undervotes":0,"Overvotes":0,"OutstackConditionIds":[],"Marks":[{"CandidateId":236,"ManifestationId":7481,"PartyId":0,"Rank":1,"MarkDensity":100,"IsAmbiguous":false,"IsVote":true,"OutstackConditionIds":[]}]}],"OutstackConditionIds":[]}]}},{"TabulatorId":939908,"BatchId":1,"RecordId":5383511,"CountingGroupId":1,"ImageMask":"D:\\NAS\\2024 General Election\\Results\\Tabulator939908\\Batch001\\Images\\939908_00001_5383511*.*","SessionType":"DreVote","VotingSessionIdentifier":"939908_d52d18e3-f9b6-41b2-9022-151b2180f2e6","UniqueVotingIdentifier":"995_a9af925c-ad1f-4357-a7c9-f00ad00111dd","Original":{"PrecinctPortionId":357,"BallotTypeId":44,"IsCurrent":true,"Cards":[{"Id":1066,"KeyInId":1066,"PaperIndex":0,"Contests":[{"Id":4,"ManifestationId":896,"Undervotes":0,"Overvotes":0,"OutstackConditionIds":[14],"Marks":[{"CandidateId":542,"ManifestationId":7370,"PartyId":7,"Rank":1,"MarkDensity":100,"IsAmbiguous":false,"IsVote":true,"OutstackConditionIds":[]}]},{"Id":7,"ManifestationId":897,"Undervotes":0,"Overvotes":0,"OutstackConditionIds":[14],"Marks":[{"CandidateId":518,"ManifestationId":7433,"PartyId":7,"Rank":1,"MarkDensity":100,"IsAmbiguous":false,"IsVote":true,"OutstackConditionIds":[]}]},{"Id":27,"ManifestationId":898,"Undervotes":0,"Overvotes":0,"OutstackConditionIds":[14],"Marks":[{"CandidateId":379,"ManifestationId":7457,"PartyId":7,"Rank":1,"MarkDensity":100,"IsAmbiguous":false,"IsVote":true,"OutstackConditionIds":[]}]},{"Id":66,"ManifestationId":899,"Undervotes":0,"Overvotes":0,"OutstackConditionIds":[14],"Marks":[{"CandidateId":461,"ManifestationId":7461,"PartyId":3,"Rank":1,"MarkDensity":100,"IsAmbiguous":false,"IsVote":true,"OutstackConditionIds":[]}]},{"Id":68,"ManifestationId":900,"Undervotes":0,"Overvotes":0,"OutstackConditionIds":[],"Marks":[{"CandidateId":217,"ManifestationId":7470,"PartyId":0,"Rank":1,"MarkDensity":100,"IsAmbiguous":false,"IsVote":true,"OutstackConditionIds":[]}]},{"Id":69,"ManifestationId":901,"Undervotes":0,"Overvotes":0,"OutstackConditionIds":[],"Marks":[{"CandidateId":220,"ManifestationId":7473,"PartyId":0,"Rank":1,"MarkDensity":100,"IsAmbiguous":false,"IsVote":true,"OutstackConditionIds":[]}]},{"Id":71,"ManifestationId":902,"Undervotes":0,"Overvotes":0,"OutstackConditionIds":[],"Marks":[{"CandidateId":223,"ManifestationId":7474,"PartyId":0,"Rank":1,"MarkDensity":100,"IsAmbiguous":false,"IsVote":true,"OutstackConditionIds":[]}]},{"Id":72,"ManifestationId":903,"Undervotes":0,"Overvotes":0,"OutstackConditionIds":[],"Marks":[{"CandidateId":225,"ManifestationId":7476,"PartyId":0,"Rank":1,"MarkDensity":100,"IsAmbiguous":false,"IsVote":true,"OutstackConditionIds":[]}]},{"Id":76,"ManifestationId":904,"Undervotes":0,"Overvotes":0,"OutstackConditionIds":[],"Marks":[{"CandidateId":233,"ManifestationId":7478,"PartyId":0,"Rank":1,"MarkDensity":100,"IsAmbiguous":false,"IsVote":true,"OutstackConditionIds":[]}]},{"Id":77,"ManifestationId":905,"Undervotes":0,"Overvotes":0,"OutstackConditionIds":[],"Marks":[{"CandidateId":235,"ManifestationId":7480,"PartyId":0,"Rank":1,"MarkDensity":100,"IsAmbiguous":false,"IsVote":true,"OutstackConditionIds":[]}]}],"OutstackConditionIds":[]}]}}]}