{"Version":"5.17.18.1","ElectionId":"2024 General Election","Sessions":[{"TabulatorId":90300,"BatchId":2,"RecordId":1,"CountingGroupId":4,"ImageMask":"D:\\NAS\\2024 General Election\\Results\\Tabulator90300\\Batch002\\Images\\90300_00002_000001*.*","SessionType":"ScannedVote","VotingSessionIdentifier":"","UniqueVotingIdentifier":"","Original":{"PrecinctPortionId":520,"BallotTypeId":45,"IsCurrent":true,"Cards":[{"Id":1071,"KeyInId":1071,"PaperIndex":0,"Contests":[{"Id":4,"ManifestationId":979,"Undervotes":0,"Overvotes":0,"OutstackConditionIds":[14],"Marks":[{"CandidateId":543,"ManifestationId":8369,"PartyId":15,"Rank":1,"MarkDensity":88,"IsAmbiguous":false,"IsVote":true,"OutstackConditionIds":[]}]},{"Id":7,"ManifestationId":980,"Undervotes":1,"Overvotes":0,"OutstackConditionIds":[13],"Marks":[]},{"Id":27,"ManifestationId":981,"Undervotes":1,"Overvotes":0,"OutstackConditionIds":[13],"Marks":[]},{"Id":67,"ManifestationId":982,"Undervotes":1,"Overvotes":0,"OutstackConditionIds":[13],"Marks":[]},{"Id":68,"ManifestationId":983,"Undervotes":1,"Overvotes":0,"OutstackConditionIds":[4,6],"Marks":[]},{"Id":69,"ManifestationId":984,"Undervotes":1,"Overvotes":0,"OutstackConditionIds":[4,6],"Marks":[]},{"Id":71,"ManifestationId":985,"Undervotes":1,"Overvotes":0,"OutstackConditionIds":[4,6],"Marks":[]},{"Id":72,"ManifestationId":986,"Undervotes":1,"Overvotes":0,"OutstackConditionIds":[4,6],"Marks":[]},{"Id":76,"ManifestationId":987,"Undervotes":1,"Overvotes":0,"OutstackConditionIds":[4,6],"Marks":[]},{"Id":77,"ManifestationId":988,"Undervotes":1,"Overvotes":0,"OutstackConditionIds":[4,6],"Marks":[]}],"OutstackConditionIds":[]}]}},{"TabulatorId":90300,"BatchId":2,"RecordId":4,"CountingGroupId":4,"ImageMask":"D:\\NAS\\2024 General Election\\Results\\Tabulator90300\\Batch002\\Images\\90300_00002_000004*.*","SessionType":"ScannedVote","VotingSessionIdentifier":"","UniqueVotingIdentifier":"","Original":{"PrecinctPortionId":520,"BallotTypeId":45,"IsCurrent":true,"Cards":[{"Id":1071,"KeyInId":1071,"PaperIndex":0,"Contests":[{"Id":4,"ManifestationId":979,"Undervotes":0,"Overvotes":0,"OutstackConditionIds":[14],"Marks":[{"CandidateId":542,"ManifestationId":8363,"PartyId":7,"Rank":1,"MarkDensity":80,"IsAmbiguous":false,"IsVote":true,"OutstackConditionIds":[]}]},{"Id":7,"ManifestationId":980,"Undervotes":0,"Overvotes":0,"OutstackConditionIds":[14],"Marks":[{"CandidateId":518,"ManifestationId":8426,"PartyId":7,"Rank":1,"MarkDensity":85,"IsAmbiguous":false,"IsVote":true,"OutstackConditionIds":[]}]},{"Id":27,"ManifestationId":981,"Undervotes":0,"Overvotes":0,"OutstackConditionIds":[14],"Marks":[{"CandidateId":379,"ManifestationId":8451,"PartyId":7,"Rank":1,"MarkDensity":87,"IsAmbiguous":false,"IsVote":true,"OutstackConditionIds":[]}]},{"Id":67,"ManifestationId":982,"Undervotes":0,"Overvotes":0,"OutstackConditionIds":[14],"Marks":[{"CandidateId":465,"ManifestationId":8457,"PartyId":7,"Rank":1,"MarkDensity":85,"IsAmbiguous":false,"IsVote":true,"OutstackConditionIds":[]}]},{"Id":68,"ManifestationId":983,"Undervotes":0,"Overvotes":0,"OutstackConditionIds":[],"Marks":[{"CandidateId":217,"ManifestationId":8471,"PartyId":0,"Rank":1,"MarkDensity":85,"IsAmbiguous":false,"IsVote":true,"OutstackConditionIds":[]}]},{"Id":69,"ManifestationId":984,"Undervotes":0,"Overvotes":0,"OutstackConditionIds":[],"Marks":[{"CandidateId":220,"ManifestationId":8474,"PartyId":0,"Rank":1,"MarkDensity":85,"IsAmbiguous":false,"IsVote":true,"OutstackConditionIds":[]}]},{"Id":71,"ManifestationId":985,"Undervotes":0,"Overvotes":0,"OutstackConditionIds":[],"Marks":[{"CandidateId":223,"ManifestationId":8475,"PartyId":0,"Rank":1,"MarkDensity":93,"IsAmbiguous":false,"IsVote":true,"OutstackConditionIds":[]}]},{"Id":72,"ManifestationId":986,"Undervotes":0,"Overvotes":0,"OutstackConditionIds":[],"Marks":[{"CandidateId":225,"ManifestationId":8477,"PartyId":0,"Rank":1,"MarkDensity":62,"IsAmbiguous":false,"IsVote":true,"OutstackConditionIds":[]}]},{"Id":76,"ManifestationId":987,"Undervotes":0,"Overvotes":0,"OutstackConditionIds":[],"Marks":[{"CandidateId":233,"ManifestationId":8479,"PartyId":0,"Rank":1,"MarkDensity":88,"IsAmbiguous":false,"IsVote":true,"OutstackConditionIds":[]}]},{"Id":77,"ManifestationId":988,"Undervotes":0,"Overvotes":0,"OutstackConditionIds":[],"Marks":[{"CandidateId":235,"ManifestationId":8481,"PartyId":0,"Rank":1,"MarkDensity":94,"IsAmbiguous":false,"IsVote":true,"OutstackConditionIds":[]}]}],"OutstackConditionIds":[]}]}},{"TabulatorId":90300,"BatchId":2,"RecordId":2,"CountingGroupId":4,"ImageMask":"D:\\NAS\\2024 General Election\\Results\\Tabulator90300\\Batch002\\Images\\90300_00002_000002*.*","SessionType":"ScannedVote","VotingSessionIdentifier":"","UniqueVotingIdentifier":"","Original":{"PrecinctPortionId":520,"BallotTypeId":45,"IsCurrent":true,"Cards":[{"Id":1071,"KeyInId":1071,"PaperIndex":0,"Contests":[{"Id":4,"ManifestationId":979,"Undervotes":0,"Overvotes":0,"OutstackConditionIds":[],"Marks":[{"CandidateId":542,"ManifestationId":8363,"PartyId":7,"Rank":1,"MarkDensity":92,"IsAmbiguous":false,"IsVote":true,"OutstackConditionIds":[]},{"CandidateId":541,"ManifestationId":8370,"PartyId":6,"Rank":2,"MarkDensity":67,"IsAmbiguous":false,"IsVote":true,"OutstackConditionIds":[]},{"CandidateId":542,"ManifestationId":8379,"PartyId":7,"Rank":3,"MarkDensity":82,"IsAmbiguous":false,"IsVote":true,"OutstackConditionIds":[12,10]},{"CandidateId":542,"ManifestationId":8387,"PartyId":7,"Rank":4,"MarkDensity":82,"IsAmbiguous":false,"IsVote":true,"OutstackConditionIds":[12,10]},{"CandidateId":542,"ManifestationId":8395,"PartyId":7,"Rank":5,"MarkDensity":80,"IsAmbiguous":false,"IsVote":true,"OutstackConditionIds":[12,10]},{"CandidateId":542,"ManifestationId":8403,"PartyId":7,"Rank":6,"MarkDensity":73,"IsAmbiguous":false,"IsVote":true,"OutstackConditionIds":[12,10]},{"CandidateId":542,"ManifestationId":8411,"PartyId":7,"Rank":7,"MarkDensity":59,"IsAmbiguous":false,"IsVote":true,"OutstackConditionIds":[12,10]},{"CandidateId":542,"ManifestationId":8419,"PartyId":7,"Rank":8,"MarkDensity":66,"IsAmbiguous":false,"IsVote":true,"OutstackConditionIds":[12,10]}]},{"Id":7,"ManifestationId":980,"Undervotes":0,"Overvotes":0,"OutstackConditionIds":[],"Marks":[{"CandidateId":518,"ManifestationId":8426,"PartyId":7,"Rank":1,"MarkDensity":84,"IsAmbiguous":false,"IsVote":true,"OutstackConditionIds":[]},{"CandidateId":518,"ManifestationId":8431,"PartyId":7,"Rank":2,"MarkDensity":76,"IsAmbiguous":false,"IsVote":true,"OutstackConditionIds":[12]},{"CandidateId":518,"ManifestationId":8436,"PartyId":7,"Rank":3,"MarkDensity":79,"IsAmbiguous":false,"IsVote":true,"OutstackConditionIds":[12]},{"CandidateId":518,"ManifestationId":8441,"PartyId":7,"Rank":4,"MarkDensity":73,"IsAmbiguous":false,"IsVote":true,"OutstackConditionIds":[12]},{"CandidateId":518,"ManifestationId":8446,"PartyId":7,"Rank":5,"MarkDensity":55,"IsAmbiguous":false,"IsVote":true,"OutstackConditionIds":[12]}]},{"Id":27,"ManifestationId":981,"Undervotes":0,"Overvotes":0,"OutstackConditionIds":[14],"Marks":[{"CandidateId":379,"ManifestationId":8451,"PartyId":7,"Rank":1,"MarkDensity":94,"IsAmbiguous":false,"IsVote":true,"OutstackConditionIds":[]}]},{"Id":67,"ManifestationId":982,"Undervotes":0,"Overvotes":0,"OutstackConditionIds":[],"Marks":[{"CandidateId":463,"ManifestationId":8455,"PartyId":7,"Rank":1,"MarkDensity":87,"IsAmbiguous":false,"IsVote":true,"OutstackConditionIds":[]},{"CandidateId":463,"ManifestationId":8459,"PartyId":7,"Rank":2,"MarkDensity":82,"IsAmbiguous":false,"IsVote":true,"OutstackConditionIds":[12]},{"CandidateId":463,"ManifestationId":8463,"PartyId":7,"Rank":3,"MarkDensity":85,"IsAmbiguous":false,"IsVote":true,"OutstackConditionIds":[12]},{"CandidateId":463,"ManifestationId":8467,"PartyId":7,"Rank":4,"MarkDensity":83,"IsAmbiguous":false,"IsVote":true,"OutstackConditionIds":[12]}]},{"Id":68,"ManifestationId":983,"Undervotes":0,"Overvotes":0,"OutstackConditionIds":[],"Marks":[{"CandidateId":217,"ManifestationId":8471,"PartyId":0,"Rank":1,"MarkDensity":86,"IsAmbiguous":false,"IsVote":true,"OutstackConditionIds":[]}]},{"Id":69,"ManifestationId":984,"Undervotes":0,"Overvotes":0,"OutstackConditionIds":[],"Marks":[{"CandidateId":219,"ManifestationId":8473,"PartyId":0,"Rank":1,"MarkDensity":78,"IsAmbiguous":false,"IsVote":true,"OutstackConditionIds":[]}]},{"Id":71,"ManifestationId":985,"Undervotes":0,"Overvotes":0,"OutstackConditionIds":[],"Marks":[{"CandidateId":223,"ManifestationId":8475,"PartyId":0,"Rank":1,"MarkDensity":90,"IsAmbiguous":false,"IsVote":true,"OutstackConditionIds":[]}]},{"Id":72,"ManifestationId":986,"Undervotes":0,"Overvotes":0,"OutstackConditionIds":[],"Marks":[{"CandidateId":225,"ManifestationId":8477,"PartyId":0,"Rank":1,"MarkDensity":80,"IsAmbiguous":false,"IsVote":true,"OutstackConditionIds":[]}]},{"Id":76,"ManifestationId":987,"Undervotes":0,"Overvotes":0,"OutstackConditionIds":[],"Marks":[{"CandidateId":233,"ManifestationId":8479,"PartyId":0,"Rank":1,"MarkDensity":87,"IsAmbiguous":false,"IsVote":true,"OutstackConditionIds":[]}]},{"Id":77,"ManifestationId":988,"Undervotes":0,"Overvotes":0,"OutstackConditionIds":[],"Marks":[{"CandidateId":235,"ManifestationId":8481,"PartyId":0,"Rank":1,"MarkDensity":79,"IsAmbiguous":false,"IsVote":true,"OutstackConditionIds":[]}]}],"OutstackConditionIds":[]}]}},{"TabulatorId":90300,"BatchId":2,"RecordId":5,"CountingGroupId":4,"ImageMask":"D:\\NAS\\2024 General Election\\Results\\Tabulator90300\\Batch002\\Images\\90300_00002_000005*.*","SessionType":"ScannedVote","VotingSessionIdentifier":"","UniqueVotingIdentifier":"","Original":{"PrecinctPortionId":520,"BallotTypeId":45,"IsCurrent":true,"Cards":[{"Id":1071,"KeyInId":1071,"PaperIndex":0,"Contests":[{"Id":4,"ManifestationId":979,"Undervotes":0,"Overvotes":0,"OutstackConditionIds":[],"Marks":[{"CandidateId":541,"ManifestationId":8362,"PartyId":6,"Rank":1,"MarkDensity":84,"IsAmbiguous":false,"IsVote":true,"OutstackConditionIds":[]},{"CandidateId":547,"ManifestationId":8374,"PartyId":19,"Rank":2,"MarkDensity":80,"IsAmbiguous":false,"IsVote":true,"OutstackConditionIds":[]},{"CandidateId":540,"ManifestationId":8381,"PartyId":10,"Rank":3,"MarkDensity":74,"IsAmbiguous":false,"IsVote":true,"OutstackConditionIds":[]},{"CandidateId":542,"ManifestationId":8387,"PartyId":7,"Rank":4,"MarkDensity":76,"IsAmbiguous":false,"IsVote":true,"OutstackConditionIds":[]},{"CandidateId":554,"ManifestationId":8396,"PartyId":18,"Rank":5,"MarkDensity":74,"IsAmbiguous":false,"IsVote":true,"OutstackConditionIds":[]},{"CandidateId":545,"ManifestationId":8407,"PartyId":18,"Rank":6,"MarkDensity":81,"IsAmbiguous":false,"IsVote":true,"OutstackConditionIds":[]},{"CandidateId":546,"ManifestationId":8416,"PartyId":5,"Rank":7,"MarkDensity":83,"IsAmbiguous":false,"IsVote":true,"OutstackConditionIds":[]},{"CandidateId":543,"ManifestationId":8425,"PartyId":15,"Rank":8,"MarkDensity":80,"IsAmbiguous":false,"IsVote":true,"OutstackConditionIds":[]}]},{"Id":7,"ManifestationId":980,"Undervotes":0,"Overvotes":0,"OutstackConditionIds":[11],"Marks":[{"CandidateId":518,"ManifestationId":8426,"PartyId":7,"Rank":1,"MarkDensity":88,"IsAmbiguous":false,"IsVote":true,"OutstackConditionIds":[]},{"CandidateId":552,"ManifestationId":8433,"PartyId":7,"Rank":2,"MarkDensity":73,"IsAmbiguous":false,"IsVote":true,"OutstackConditionIds":[]},{"CandidateId":520,"ManifestationId":8439,"PartyId":3,"Rank":3,"MarkDensity":85,"IsAmbiguous":false,"IsVote":true,"OutstackConditionIds":[]},{"CandidateId":517,"ManifestationId":8447,"PartyId":15,"Rank":5,"MarkDensity":85,"IsAmbiguous":false,"IsVote":true,"OutstackConditionIds":[]}]},{"Id":27,"ManifestationId":981,"Undervotes":0,"Overvotes":0,"OutstackConditionIds":[14],"Marks":[{"CandidateId":379,"ManifestationId":8451,"PartyId":7,"Rank":1,"MarkDensity":84,"IsAmbiguous":false,"IsVote":true,"OutstackConditionIds":[]}]},{"Id":67,"ManifestationId":982,"Undervotes":0,"Overvotes":0,"OutstackConditionIds":[14],"Marks":[{"CandidateId":465,"ManifestationId":8457,"PartyId":7,"Rank":1,"MarkDensity":82,"IsAmbiguous":false,"IsVote":true,"OutstackConditionIds":[]},{"CandidateId":463,"ManifestationId":8459,"PartyId":7,"Rank":2,"MarkDensity":87,"IsAmbiguous":false,"IsVote":true,"OutstackConditionIds":[]},{"CandidateId":464,"ManifestationId":8464,"PartyId":2,"Rank":3,"MarkDensity":80,"IsAmbiguous":false,"IsVote":true,"OutstackConditionIds":[]}]},{"Id":68,"ManifestationId":983,"Undervotes":0,"Overvotes":0,"OutstackConditionIds":[],"Marks":[{"CandidateId":218,"ManifestationId":8472,"PartyId":0,"Rank":1,"MarkDensity":73,"IsAmbiguous":false,"IsVote":true,"OutstackConditionIds":[]}]},{"Id":69,"ManifestationId":984,"Undervotes":0,"Overvotes":0,"OutstackConditionIds":[],"Marks":[{"CandidateId":220,"ManifestationId":8474,"PartyId":0,"Rank":1,"MarkDensity":91,"IsAmbiguous":false,"IsVote":true,"OutstackConditionIds":[]}]},{"Id":71,"ManifestationId":985,"Undervotes":0,"Overvotes":0,"OutstackConditionIds":[],"Marks":[{"CandidateId":224,"ManifestationId":8476,"PartyId":0,"Rank":1,"MarkDensity":88,"IsAmbiguous":false,"IsVote":true,"OutstackConditionIds":[]}]},{"Id":72,"ManifestationId":986,"Undervotes":0,"Overvotes":0,"OutstackConditionIds":[],"Marks":[{"CandidateId":225,"ManifestationId":8477,"PartyId":0,"Rank":1,"MarkDensity":80,"IsAmbiguous":false,"IsVote":true,"OutstackConditionIds":[]}]},{"Id":76,"ManifestationId":987,"Undervotes":0,"Overvotes":0,"OutstackConditionIds":[],"Marks":[{"CandidateId":233,"ManifestationId":8479,"PartyId":0,"Rank":1,"MarkDensity":86,"IsAmbiguous":false,"IsVote":true,"OutstackConditionIds":[]}]},{"Id":77,"ManifestationId":988,"Undervotes":0,"Overvotes":0,"OutstackConditionIds":[],"Marks":[{"CandidateId":235,"ManifestationId":8481,"PartyId":0,"Rank":1,"MarkDensity":70,"IsAmbiguous":false,"IsVote":true,"OutstackConditionIds":[]}]}],"OutstackConditionIds":[]}]}},{"TabulatorId":90300,"BatchId":2,"RecordId":6,"CountingGroupId":4,"ImageMask":"D:\\NAS\\2024 General Election\\Results\\Tabulator90300\\Batch002\\Images\\90300_00002_000006*.*","SessionType":"ScannedVote","VotingSessionIdentifier":"","UniqueVotingIdentifier":"","Original":{"PrecinctPortionId":520,"BallotTypeId":45,"IsCurrent":true,"Cards":[{"Id":1071,"KeyInId":1071,"PaperIndex":0,"Contests":[{"Id":4,"ManifestationId":979,"Undervotes":0,"Overvotes":0,"OutstackConditionIds":[],"Marks":[{"CandidateId":543,"ManifestationId":8369,"PartyId":15,"Rank":1,"MarkDensity":84,"IsAmbiguous":false,"IsVote":true,"OutstackConditionIds":[]},{"CandidateId":545,"ManifestationId":8375,"PartyId":18,"Rank":2,"MarkDensity":74,"IsAmbiguous":false,"IsVote":true,"OutstackConditionIds":[]},{"CandidateId":540,"ManifestationId":8381,"PartyId":10,"Rank":3,"MarkDensity":65,"IsAmbiguous":false,"IsVote":true,"OutstackConditionIds":[]},{"CandidateId":542,"ManifestationId":8387,"PartyId":7,"Rank":4,"MarkDensity":56,"IsAmbiguous":false,"IsVote":true,"OutstackConditionIds":[]},{"CandidateId":546,"ManifestationId":8400,"PartyId":5,"Rank":5,"MarkDensity":76,"IsAmbiguous":false,"IsVote":true,"OutstackConditionIds":[]},{"CandidateId":554,"ManifestationId":8404,"PartyId":18,"Rank":6,"MarkDensity":82,"IsAmbiguous":false,"IsVote":true,"OutstackConditionIds":[]},{"CandidateId":541,"ManifestationId":8410,"PartyId":6,"Rank":7,"MarkDensity":60,"IsAmbiguous":false,"IsVote":true,"OutstackConditionIds":[]},{"CandidateId":542,"ManifestationId":8419,"PartyId":7,"Rank":8,"MarkDensity":76,"IsAmbiguous":false,"IsVote":true,"OutstackConditionIds":[12,10]}]},{"Id":7,"ManifestationId":980,"Undervotes":0,"Overvotes":0,"OutstackConditionIds":[],"Marks":[{"CandidateId":517,"ManifestationId":8427,"PartyId":15,"Rank":1,"MarkDensity":68,"IsAmbiguous":false,"IsVote":true,"OutstackConditionIds":[]},{"CandidateId":520,"ManifestationId":8434,"PartyId":3,"Rank":2,"MarkDensity":58,"IsAmbiguous":false,"IsVote":true,"OutstackConditionIds":[]},{"CandidateId":552,"ManifestationId":8438,"PartyId":7,"Rank":3,"MarkDensity":56,"IsAmbiguous":false,"IsVote":true,"OutstackConditionIds":[]},{"CandidateId":518,"ManifestationId":8441,"PartyId":7,"Rank":4,"MarkDensity":82,"IsAmbiguous":false,"IsVote":true,"OutstackConditionIds":[]},{"CandidateId":518,"ManifestationId":8446,"PartyId":7,"Rank":5,"MarkDensity":73,"IsAmbiguous":false,"IsVote":true,"OutstackConditionIds":[12]}]},{"Id":27,"ManifestationId":981,"Undervotes":1,"Overvotes":0,"OutstackConditionIds":[13],"Marks":[]},{"Id":67,"ManifestationId":982,"Undervotes":0,"Overvotes":0,"OutstackConditionIds":[14],"Marks":[{"CandidateId":463,"ManifestationId":8455,"PartyId":7,"Rank":1,"MarkDensity":87,"IsAmbiguous":false,"IsVote":true,"OutstackConditionIds":[]},{"CandidateId":465,"ManifestationId":8461,"PartyId":7,"Rank":2,"MarkDensity":84,"IsAmbiguous":false,"IsVote":true,"OutstackConditionIds":[]},{"CandidateId":464,"ManifestationId":8464,"PartyId":2,"Rank":3,"MarkDensity":79,"IsAmbiguous":false,"IsVote":true,"OutstackConditionIds":[]}]},{"Id":68,"ManifestationId":983,"Undervotes":0,"Overvotes":0,"OutstackConditionIds":[],"Marks":[{"CandidateId":217,"ManifestationId":8471,"PartyId":0,"Rank":1,"MarkDensity":96,"IsAmbiguous":false,"IsVote":true,"OutstackConditionIds":[]}]},{"Id":69,"ManifestationId":984,"Undervotes":0,"Overvotes":0,"OutstackConditionIds":[],"Marks":[{"CandidateId":219,"ManifestationId":8473,"PartyId":0,"Rank":1,"MarkDensity":70,"IsAmbiguous":false,"IsVote":true,"OutstackConditionIds":[]}]},{"Id":71,"ManifestationId":985,"Undervotes":0,"Overvotes":0,"OutstackConditionIds":[],"Marks":[{"CandidateId":224,"ManifestationId":8476,"PartyId":0,"Rank":1,"MarkDensity":83,"IsAmbiguous":false,"IsVote":true,"OutstackConditionIds":[]}]},{"Id":72,"ManifestationId":986,"Undervotes":0,"Overvotes":0,"OutstackConditionIds":[],"Marks":[{"CandidateId":226,"ManifestationId":8478,"PartyId":0,"Rank":1,"MarkDensity":87,"IsAmbiguous":false,"IsVote":true,"OutstackConditionIds":[]}]},{"Id":76,"ManifestationId":987,"Undervotes":0,"Overvotes":0,"OutstackConditionIds":[],"Marks":[{"CandidateId":234,"ManifestationId":8480,"PartyId":0,"Rank":1,"MarkDensity":80,"IsAmbiguous":false,"IsVote":true,"OutstackConditionIds":[]}]},{"Id":77,"ManifestationId":988,"Undervotes":0,"Overvotes":0,"OutstackConditionIds":[],"Marks":[{"CandidateId":236,"ManifestationId":8482,"PartyId":0,"Rank":1,"MarkDensity":88,"IsAmbiguous":false,"IsVote":true,"OutstackConditionIds":[]}]}],"OutstackConditionIds":[]}]}},{"TabulatorId":90300,"BatchId":2,"RecordId":3,"CountingGroupId":4,"ImageMask":"D:\\NAS\\2024 General Election\\Results\\Tabulator90300\\Batch002\\Images\\90300_00002_000003*.*","SessionType":"ScannedVote","VotingSessionIdentifier":"","UniqueVotingIdentifier":"","Original":{"PrecinctPortionId":520,"BallotTypeId":45,"IsCurrent":true,"Cards":[{"Id":1071,"KeyInId":1071,"PaperIndex":0,"Contests":[{"Id":4,"ManifestationId":979,"Undervotes":0,"Overvotes":0,"OutstackConditionIds":[14],"Marks":[{"CandidateId":543,"ManifestationId":8369,"PartyId":15,"Rank":1,"MarkDensity":74,"IsAmbiguous":false,"IsVote":true,"OutstackConditionIds":[]}]},{"Id":7,"ManifestationId":980,"Undervotes":0,"Overvotes":0,"OutstackConditionIds":[14],"Marks":[{"CandidateId":518,"ManifestationId":8426,"PartyId":7,"Rank":1,"MarkDensity":91,"IsAmbiguous":false,"IsVote":true,"OutstackConditionIds":[]}]},{"Id":27,"ManifestationId":981,"Undervotes":0,"Overvotes":0,"OutstackConditionIds":[14],"Marks":[{"CandidateId":379,"ManifestationId":8451,"PartyId":7,"Rank":1,"MarkDensity":84,"IsAmbiguous":false,"IsVote":true,"OutstackConditionIds":[]}]},{"Id":67,"ManifestationId":982,"Undervotes":0,"Overvotes":0,"OutstackConditionIds":[14],"Marks":[{"CandidateId":463,"ManifestationId":8455,"PartyId":7,"Rank":1,"MarkDensity":95,"IsAmbiguous":false,"IsVote":true,"OutstackConditionIds":[]}]},{"Id":68,"ManifestationId":983,"Undervotes":1,"Overvotes":0,"OutstackConditionIds":[4,6],"Marks":[]},{"Id":69,"ManifestationId":984,"Undervotes":1,"Overvotes":0,"OutstackConditionIds":[4,6],"Marks":[]},{"Id":71,"ManifestationId":985,"Undervotes":1,"Overvotes":0,"OutstackConditionIds":[4,6],"Marks":[]},{"Id":72,"ManifestationId":986,"Undervotes":1,"Overvotes":0,"OutstackConditionIds":[4,6],"Marks":[]},{"Id":76,"ManifestationId":987,"Undervotes":1,"Overvotes":0,"OutstackConditionIds":[4,6],"Marks":[]},{"Id":77,"ManifestationId":988,"Undervotes":1,"Overvotes":0,"OutstackConditionIds":[4,6],"Marks":[]}],"OutstackConditionIds":[]}]}}]}