{"Version":"5.17.18.1","ElectionId":"2024 General Election","Sessions":[{"TabulatorId":937709,"BatchId":1,"RecordId":6379161,"CountingGroupId":1,"ImageMask":"D:\\NAS\\2024 General Election\\Results\\Tabulator937709\\Batch001\\Images\\937709_00001_6379161*.*","SessionType":"DreVote","VotingSessionIdentifier":"937709_aee4959d-771f-4188-8d13-c1f711ca0558","UniqueVotingIdentifier":"937_68f4178a-5777-4449-a476-91d865edcab0","Original":{"PrecinctPortionId":299,"BallotTypeId":41,"IsCurrent":true,"Cards":[{"Id":1053,"KeyInId":1053,"PaperIndex":0,"Contests":[{"Id":4,"ManifestationId":792,"Undervotes":0,"Overvotes":0,"OutstackConditionIds":[14],"Marks":[{"CandidateId":543,"ManifestationId":6103,"PartyId":15,"Rank":1,"MarkDensity":100,"IsAmbiguous":false,"IsVote":true,"OutstackConditionIds":[]}]},{"Id":7,"ManifestationId":793,"Undervotes":0,"Overvotes":0,"OutstackConditionIds":[14],"Marks":[{"CandidateId":517,"ManifestationId":6165,"PartyId":15,"Rank":1,"MarkDensity":100,"IsAmbiguous":false,"IsVote":true,"OutstackConditionIds":[]}]},{"Id":64,"ManifestationId":794,"Undervotes":0,"Overvotes":0,"OutstackConditionIds":[14],"Marks":[{"CandidateId":455,"ManifestationId":6190,"PartyId":2,"Rank":1,"MarkDensity":100,"IsAmbiguous":false,"IsVote":true,"OutstackConditionIds":[]}]},{"Id":68,"ManifestationId":795,"Undervotes":0,"Overvotes":0,"OutstackConditionIds":[],"Marks":[{"CandidateId":217,"ManifestationId":6199,"PartyId":0,"Rank":1,"MarkDensity":100,"IsAmbiguous":false,"IsVote":true,"OutstackConditionIds":[]}]},{"Id":69,"ManifestationId":796,"Undervotes":0,"Overvotes":0,"OutstackConditionIds":[],"Marks":[{"CandidateId":220,"ManifestationId":6202,"PartyId":0,"Rank":1,"MarkDensity":100,"IsAmbiguous":false,"IsVote":true,"OutstackConditionIds":[]}]},{"Id":71,"ManifestationId":797,"Undervotes":0,"Overvotes":0,"OutstackConditionIds":[],"Marks":[{"CandidateId":224,"ManifestationId":6204,"PartyId":0,"Rank":1,"MarkDensity":100,"IsAmbiguous":false,"IsVote":true,"OutstackConditionIds":[]}]},{"Id":72,"ManifestationId":798,"Undervotes":0,"Overvotes":0,"OutstackConditionIds":[],"Marks":[{"CandidateId":226,"ManifestationId":6206,"PartyId":0,"Rank":1,"MarkDensity":100,"IsAmbiguous":false,"IsVote":true,"OutstackConditionIds":[]}]},{"Id":76,"ManifestationId":799,"Undervotes":0,"Overvotes":0,"OutstackConditionIds":[],"Marks":[{"CandidateId":234,"ManifestationId":6208,"PartyId":0,"Rank":1,"MarkDensity":100,"IsAmbiguous":false,"IsVote":true,"OutstackConditionIds":[]}]},{"Id":77,"ManifestationId":800,"Undervotes":0,"Overvotes":0,"OutstackConditionIds":[],"Marks":[{"CandidateId":236,"ManifestationId":6210,"PartyId":0,"Rank":1,"MarkDensity":100,"IsAmbiguous":false,"IsVote":true,"OutstackConditionIds":[]}]},{"Id":129,"ManifestationId":801,"Undervotes":0,"Overvotes":0,"OutstackConditionIds":[],"Marks":[{"CandidateId":340,"ManifestationId":6212,"PartyId":0,"Rank":1,"MarkDensity":100,"IsAmbiguous":false,"IsVote":true,"OutstackConditionIds":[]}]},{"Id":137,"ManifestationId":802,"Undervotes":0,"Overvotes":0,"OutstackConditionIds":[],"Marks":[{"CandidateId":356,"ManifestationId":6214,"PartyId":0,"Rank":1,"MarkDensity":100,"IsAmbiguous":false,"IsVote":true,"OutstackConditionIds":[]}]},{"Id":138,"ManifestationId":803,"Undervotes":0,"Overvotes":0,"OutstackConditionIds":[],"Marks":[{"CandidateId":357,"ManifestationId":6215,"PartyId":0,"Rank":1,"MarkDensity":100,"IsAmbiguous":false,"IsVote":true,"OutstackConditionIds":[]}]}],"OutstackConditionIds":[]}]}},{"TabulatorId":937709,"BatchId":1,"RecordId":6587030,"CountingGroupId":1,"ImageMask":"D:\\NAS\\2024 General Election\\Results\\Tabulator937709\\Batch001\\Images\\937709_00001_6587030*.*","SessionType":"DreVote","VotingSessionIdentifier":"937709_aee4959d-771f-4188-8d13-c1f711ca0558","UniqueVotingIdentifier":"937_8fe0d8c6-8916-4f7d-80be-b5cbb3d51f4b","Original":{"PrecinctPortionId":299,"BallotTypeId":41,"IsCurrent":true,"Cards":[{"Id":1053,"KeyInId":1053,"PaperIndex":0,"Contests":[{"Id":4,"ManifestationId":792,"Undervotes":0,"Overvotes":0,"OutstackConditionIds":[14],"Marks":[{"CandidateId":542,"ManifestationId":6105,"PartyId":7,"Rank":1,"MarkDensity":100,"IsAmbiguous":false,"IsVote":true,"OutstackConditionIds":[]}]},{"Id":7,"ManifestationId":793,"Undervotes":0,"Overvotes":0,"OutstackConditionIds":[14],"Marks":[{"CandidateId":518,"ManifestationId":6168,"PartyId":7,"Rank":1,"MarkDensity":100,"IsAmbiguous":false,"IsVote":true,"OutstackConditionIds":[]}]},{"Id":64,"ManifestationId":794,"Undervotes":0,"Overvotes":0,"OutstackConditionIds":[14],"Marks":[{"CandidateId":456,"ManifestationId":6191,"PartyId":1,"Rank":1,"MarkDensity":100,"IsAmbiguous":false,"IsVote":true,"OutstackConditionIds":[]}]},{"Id":68,"ManifestationId":795,"Undervotes":0,"Overvotes":0,"OutstackConditionIds":[],"Marks":[{"CandidateId":218,"ManifestationId":6200,"PartyId":0,"Rank":1,"MarkDensity":100,"IsAmbiguous":false,"IsVote":true,"OutstackConditionIds":[]}]},{"Id":69,"ManifestationId":796,"Undervotes":0,"Overvotes":0,"OutstackConditionIds":[],"Marks":[{"CandidateId":220,"ManifestationId":6202,"PartyId":0,"Rank":1,"MarkDensity":100,"IsAmbiguous":false,"IsVote":true,"OutstackConditionIds":[]}]},{"Id":71,"ManifestationId":797,"Undervotes":0,"Overvotes":0,"OutstackConditionIds":[],"Marks":[{"CandidateId":224,"ManifestationId":6204,"PartyId":0,"Rank":1,"MarkDensity":100,"IsAmbiguous":false,"IsVote":true,"OutstackConditionIds":[]}]},{"Id":72,"ManifestationId":798,"Undervotes":0,"Overvotes":0,"OutstackConditionIds":[],"Marks":[{"CandidateId":226,"ManifestationId":6206,"PartyId":0,"Rank":1,"MarkDensity":100,"IsAmbiguous":false,"IsVote":true,"OutstackConditionIds":[]}]},{"Id":76,"ManifestationId":799,"Undervotes":0,"Overvotes":0,"OutstackConditionIds":[],"Marks":[{"CandidateId":234,"ManifestationId":6208,"PartyId":0,"Rank":1,"MarkDensity":100,"IsAmbiguous":false,"IsVote":true,"OutstackConditionIds":[]}]},{"Id":77,"ManifestationId":800,"Undervotes":0,"Overvotes":0,"OutstackConditionIds":[],"Marks":[{"CandidateId":236,"ManifestationId":6210,"PartyId":0,"Rank":1,"MarkDensity":100,"IsAmbiguous":false,"IsVote":true,"OutstackConditionIds":[]}]},{"Id":129,"ManifestationId":801,"Undervotes":0,"Overvotes":0,"OutstackConditionIds":[],"Marks":[{"CandidateId":340,"ManifestationId":6212,"PartyId":0,"Rank":1,"MarkDensity":100,"IsAmbiguous":false,"IsVote":true,"OutstackConditionIds":[]}]},{"Id":137,"ManifestationId":802,"Undervotes":0,"Overvotes":0,"OutstackConditionIds":[],"Marks":[{"CandidateId":356,"ManifestationId":6214,"PartyId":0,"Rank":1,"MarkDensity":100,"IsAmbiguous":false,"IsVote":true,"OutstackConditionIds":[]}]},{"Id":138,"ManifestationId":803,"Undervotes":0,"Overvotes":0,"OutstackConditionIds":[],"Marks":[{"CandidateId":358,"ManifestationId":6216,"PartyId":0,"Rank":1,"MarkDensity":100,"IsAmbiguous":false,"IsVote":true,"OutstackConditionIds":[]}]}],"OutstackConditionIds":[]}]}},{"TabulatorId":937709,"BatchId":1,"RecordId":9551455,"CountingGroupId":1,"ImageMask":"D:\\NAS\\2024 General Election\\Results\\Tabulator937709\\Batch001\\Images\\937709_00001_9551455*.*","SessionType":"DreVote","VotingSessionIdentifier":"937709_aee4959d-771f-4188-8d13-c1f711ca0558","UniqueVotingIdentifier":"937_dc2437c8-30e5-4c92-9b19-3f2b66cc3dfb","Original":{"PrecinctPortionId":299,"BallotTypeId":41,"IsCurrent":true,"Cards":[{"Id":1053,"KeyInId":1053,"PaperIndex":0,"Contests":[{"Id":4,"ManifestationId":792,"Undervotes":0,"Overvotes":0,"OutstackConditionIds":[14],"Marks":[{"CandidateId":543,"ManifestationId":6103,"PartyId":15,"Rank":1,"MarkDensity":100,"IsAmbiguous":false,"IsVote":true,"OutstackConditionIds":[]}]},{"Id":7,"ManifestationId":793,"Undervotes":0,"Overvotes":0,"OutstackConditionIds":[14],"Marks":[{"CandidateId":518,"ManifestationId":6168,"PartyId":7,"Rank":1,"MarkDensity":100,"IsAmbiguous":false,"IsVote":true,"OutstackConditionIds":[]}]},{"Id":64,"ManifestationId":794,"Undervotes":0,"Overvotes":0,"OutstackConditionIds":[14],"Marks":[{"CandidateId":456,"ManifestationId":6191,"PartyId":1,"Rank":1,"MarkDensity":100,"IsAmbiguous":false,"IsVote":true,"OutstackConditionIds":[]}]},{"Id":68,"ManifestationId":795,"Undervotes":0,"Overvotes":0,"OutstackConditionIds":[],"Marks":[{"CandidateId":217,"ManifestationId":6199,"PartyId":0,"Rank":1,"MarkDensity":100,"IsAmbiguous":false,"IsVote":true,"OutstackConditionIds":[]}]},{"Id":69,"ManifestationId":796,"Undervotes":0,"Overvotes":0,"OutstackConditionIds":[],"Marks":[{"CandidateId":220,"ManifestationId":6202,"PartyId":0,"Rank":1,"MarkDensity":100,"IsAmbiguous":false,"IsVote":true,"OutstackConditionIds":[]}]},{"Id":71,"ManifestationId":797,"Undervotes":0,"Overvotes":0,"OutstackConditionIds":[],"Marks":[{"CandidateId":224,"ManifestationId":6204,"PartyId":0,"Rank":1,"MarkDensity":100,"IsAmbiguous":false,"IsVote":true,"OutstackConditionIds":[]}]},{"Id":72,"ManifestationId":798,"Undervotes":0,"Overvotes":0,"OutstackConditionIds":[],"Marks":[{"CandidateId":226,"ManifestationId":6206,"PartyId":0,"Rank":1,"MarkDensity":100,"IsAmbiguous":false,"IsVote":true,"OutstackConditionIds":[]}]},{"Id":76,"ManifestationId":799,"Undervotes":0,"Overvotes":0,"OutstackConditionIds":[],"Marks":[{"CandidateId":234,"ManifestationId":6208,"PartyId":0,"Rank":1,"MarkDensity":100,"IsAmbiguous":false,"IsVote":true,"OutstackConditionIds":[]}]},{"Id":77,"ManifestationId":800,"Undervotes":0,"Overvotes":0,"OutstackConditionIds":[],"Marks":[{"CandidateId":236,"ManifestationId":6210,"PartyId":0,"Rank":1,"MarkDensity":100,"IsAmbiguous":false,"IsVote":true,"OutstackConditionIds":[]}]},{"Id":129,"ManifestationId":801,"Undervotes":0,"Overvotes":0,"OutstackConditionIds":[],"Marks":[{"CandidateId":340,"ManifestationId":6212,"PartyId":0,"Rank":1,"MarkDensity":100,"IsAmbiguous":false,"IsVote":true,"OutstackConditionIds":[]}]},{"Id":137,"ManifestationId":802,"Undervotes":0,"Overvotes":0,"OutstackConditionIds":[],"Marks":[{"CandidateId":356,"ManifestationId":6214,"PartyId":0,"Rank":1,"MarkDensity":100,"IsAmbiguous":false,"IsVote":true,"OutstackConditionIds":[]}]},{"Id":138,"ManifestationId":803,"Undervotes":0,"Overvotes":0,"OutstackConditionIds":[],"Marks":[{"CandidateId":358,"ManifestationId":6216,"PartyId":0,"Rank":1,"MarkDensity":100,"IsAmbiguous":false,"IsVote":true,"OutstackConditionIds":[]}]}],"OutstackConditionIds":[]}]}},{"TabulatorId":937709,"BatchId":1,"RecordId":3902211,"CountingGroupId":1,"ImageMask":"D:\\NAS\\2024 General Election\\Results\\Tabulator937709\\Batch001\\Images\\937709_00001_3902211*.*","SessionType":"DreVote","VotingSessionIdentifier":"937709_aee4959d-771f-4188-8d13-c1f711ca0558","UniqueVotingIdentifier":"937_b4adcd16-34c3-4cff-8fe7-dd3ff0fa730a","Original":{"PrecinctPortionId":299,"BallotTypeId":41,"IsCurrent":true,"Cards":[{"Id":1053,"KeyInId":1053,"PaperIndex":0,"Contests":[{"Id":4,"ManifestationId":792,"Undervotes":0,"Overvotes":0,"OutstackConditionIds":[14],"Marks":[{"CandidateId":545,"ManifestationId":6101,"PartyId":18,"Rank":1,"MarkDensity":100,"IsAmbiguous":false,"IsVote":true,"OutstackConditionIds":[]},{"CandidateId":546,"ManifestationId":6110,"PartyId":5,"Rank":2,"MarkDensity":100,"IsAmbiguous":false,"IsVote":true,"OutstackConditionIds":[]},{"CandidateId":543,"ManifestationId":6119,"PartyId":15,"Rank":3,"MarkDensity":100,"IsAmbiguous":false,"IsVote":true,"OutstackConditionIds":[]}]},{"Id":7,"ManifestationId":793,"Undervotes":0,"Overvotes":0,"OutstackConditionIds":[14],"Marks":[{"CandidateId":518,"ManifestationId":6168,"PartyId":7,"Rank":1,"MarkDensity":100,"IsAmbiguous":false,"IsVote":true,"OutstackConditionIds":[]}]},{"Id":64,"ManifestationId":794,"Undervotes":0,"Overvotes":0,"OutstackConditionIds":[14],"Marks":[{"CandidateId":456,"ManifestationId":6191,"PartyId":1,"Rank":1,"MarkDensity":100,"IsAmbiguous":false,"IsVote":true,"OutstackConditionIds":[]}]},{"Id":68,"ManifestationId":795,"Undervotes":0,"Overvotes":0,"OutstackConditionIds":[],"Marks":[{"CandidateId":218,"ManifestationId":6200,"PartyId":0,"Rank":1,"MarkDensity":100,"IsAmbiguous":false,"IsVote":true,"OutstackConditionIds":[]}]},{"Id":69,"ManifestationId":796,"Undervotes":0,"Overvotes":0,"OutstackConditionIds":[],"Marks":[{"CandidateId":220,"ManifestationId":6202,"PartyId":0,"Rank":1,"MarkDensity":100,"IsAmbiguous":false,"IsVote":true,"OutstackConditionIds":[]}]},{"Id":71,"ManifestationId":797,"Undervotes":0,"Overvotes":0,"OutstackConditionIds":[],"Marks":[{"CandidateId":224,"ManifestationId":6204,"PartyId":0,"Rank":1,"MarkDensity":100,"IsAmbiguous":false,"IsVote":true,"OutstackConditionIds":[]}]},{"Id":72,"ManifestationId":798,"Undervotes":0,"Overvotes":0,"OutstackConditionIds":[],"Marks":[{"CandidateId":225,"ManifestationId":6205,"PartyId":0,"Rank":1,"MarkDensity":100,"IsAmbiguous":false,"IsVote":true,"OutstackConditionIds":[]}]},{"Id":76,"ManifestationId":799,"Undervotes":0,"Overvotes":0,"OutstackConditionIds":[],"Marks":[{"CandidateId":234,"ManifestationId":6208,"PartyId":0,"Rank":1,"MarkDensity":100,"IsAmbiguous":false,"IsVote":true,"OutstackConditionIds":[]}]},{"Id":77,"ManifestationId":800,"Undervotes":0,"Overvotes":0,"OutstackConditionIds":[],"Marks":[{"CandidateId":236,"ManifestationId":6210,"PartyId":0,"Rank":1,"MarkDensity":100,"IsAmbiguous":false,"IsVote":true,"OutstackConditionIds":[]}]},{"Id":129,"ManifestationId":801,"Undervotes":0,"Overvotes":0,"OutstackConditionIds":[],"Marks":[{"CandidateId":340,"ManifestationId":6212,"PartyId":0,"Rank":1,"MarkDensity":100,"IsAmbiguous":false,"IsVote":true,"OutstackConditionIds":[]}]},{"Id":137,"ManifestationId":802,"Undervotes":0,"Overvotes":0,"OutstackConditionIds":[],"Marks":[{"CandidateId":356,"ManifestationId":6214,"PartyId":0,"Rank":1,"MarkDensity":100,"IsAmbiguous":false,"IsVote":true,"OutstackConditionIds":[]}]},{"Id":138,"ManifestationId":803,"Undervotes":0,"Overvotes":0,"OutstackConditionIds":[],"Marks":[{"CandidateId":358,"ManifestationId":6216,"PartyId":0,"Rank":1,"MarkDensity":100,"IsAmbiguous":false,"IsVote":true,"OutstackConditionIds":[]}]}],"OutstackConditionIds":[]}]}},{"TabulatorId":937709,"BatchId":1,"RecordId":4402294,"CountingGroupId":1,"ImageMask":"D:\\NAS\\2024 General Election\\Results\\Tabulator937709\\Batch001\\Images\\937709_00001_4402294*.*","SessionType":"DreVote","VotingSessionIdentifier":"937709_aee4959d-771f-4188-8d13-c1f711ca0558","UniqueVotingIdentifier":"937_a2aa0716-21e9-404d-836b-6ac66882698e","Original":{"PrecinctPortionId":299,"BallotTypeId":41,"IsCurrent":true,"Cards":[{"Id":1053,"KeyInId":1053,"PaperIndex":0,"Contests":[{"Id":4,"ManifestationId":792,"Undervotes":0,"Overvotes":0,"OutstackConditionIds":[14],"Marks":[{"CandidateId":543,"ManifestationId":6103,"PartyId":15,"Rank":1,"MarkDensity":100,"IsAmbiguous":false,"IsVote":true,"OutstackConditionIds":[]}]},{"Id":7,"ManifestationId":793,"Undervotes":0,"Overvotes":0,"OutstackConditionIds":[14],"Marks":[{"CandidateId":517,"ManifestationId":6165,"PartyId":15,"Rank":1,"MarkDensity":100,"IsAmbiguous":false,"IsVote":true,"OutstackConditionIds":[]}]},{"Id":64,"ManifestationId":794,"Undervotes":0,"Overvotes":0,"OutstackConditionIds":[14],"Marks":[{"CandidateId":456,"ManifestationId":6191,"PartyId":1,"Rank":1,"MarkDensity":100,"IsAmbiguous":false,"IsVote":true,"OutstackConditionIds":[]}]},{"Id":68,"ManifestationId":795,"Undervotes":0,"Overvotes":0,"OutstackConditionIds":[],"Marks":[{"CandidateId":218,"ManifestationId":6200,"PartyId":0,"Rank":1,"MarkDensity":100,"IsAmbiguous":false,"IsVote":true,"OutstackConditionIds":[]}]},{"Id":69,"ManifestationId":796,"Undervotes":0,"Overvotes":0,"OutstackConditionIds":[],"Marks":[{"CandidateId":220,"ManifestationId":6202,"PartyId":0,"Rank":1,"MarkDensity":100,"IsAmbiguous":false,"IsVote":true,"OutstackConditionIds":[]}]},{"Id":71,"ManifestationId":797,"Undervotes":0,"Overvotes":0,"OutstackConditionIds":[],"Marks":[{"CandidateId":224,"ManifestationId":6204,"PartyId":0,"Rank":1,"MarkDensity":100,"IsAmbiguous":false,"IsVote":true,"OutstackConditionIds":[]}]},{"Id":72,"ManifestationId":798,"Undervotes":0,"Overvotes":0,"OutstackConditionIds":[],"Marks":[{"CandidateId":226,"ManifestationId":6206,"PartyId":0,"Rank":1,"MarkDensity":100,"IsAmbiguous":false,"IsVote":true,"OutstackConditionIds":[]}]},{"Id":76,"ManifestationId":799,"Undervotes":0,"Overvotes":0,"OutstackConditionIds":[],"Marks":[{"CandidateId":233,"ManifestationId":6207,"PartyId":0,"Rank":1,"MarkDensity":100,"IsAmbiguous":false,"IsVote":true,"OutstackConditionIds":[]}]},{"Id":77,"ManifestationId":800,"Undervotes":0,"Overvotes":0,"OutstackConditionIds":[],"Marks":[{"CandidateId":236,"ManifestationId":6210,"PartyId":0,"Rank":1,"MarkDensity":100,"IsAmbiguous":false,"IsVote":true,"OutstackConditionIds":[]}]},{"Id":129,"ManifestationId":801,"Undervotes":0,"Overvotes":0,"OutstackConditionIds":[],"Marks":[{"CandidateId":339,"ManifestationId":6211,"PartyId":0,"Rank":1,"MarkDensity":100,"IsAmbiguous":false,"IsVote":true,"OutstackConditionIds":[]}]},{"Id":137,"ManifestationId":802,"Undervotes":0,"Overvotes":0,"OutstackConditionIds":[],"Marks":[{"CandidateId":356,"ManifestationId":6214,"PartyId":0,"Rank":1,"MarkDensity":100,"IsAmbiguous":false,"IsVote":true,"OutstackConditionIds":[]}]},{"Id":138,"ManifestationId":803,"Undervotes":0,"Overvotes":0,"OutstackConditionIds":[],"Marks":[{"CandidateId":358,"ManifestationId":6216,"PartyId":0,"Rank":1,"MarkDensity":100,"IsAmbiguous":false,"IsVote":true,"OutstackConditionIds":[]}]}],"OutstackConditionIds":[]}]}},{"TabulatorId":937709,"BatchId":1,"RecordId":4521215,"CountingGroupId":1,"ImageMask":"D:\\NAS\\2024 General Election\\Results\\Tabulator937709\\Batch001\\Images\\937709_00001_4521215*.*","SessionType":"DreVote","VotingSessionIdentifier":"937709_aee4959d-771f-4188-8d13-c1f711ca0558","UniqueVotingIdentifier":"937_5bcb65b6-00c8-4c5a-b95c-654fda189765","Original":{"PrecinctPortionId":299,"BallotTypeId":41,"IsCurrent":true,"Cards":[{"Id":1053,"KeyInId":1053,"PaperIndex":0,"Contests":[{"Id":4,"ManifestationId":792,"Undervotes":0,"Overvotes":0,"OutstackConditionIds":[14],"Marks":[{"CandidateId":543,"ManifestationId":6103,"PartyId":15,"Rank":1,"MarkDensity":100,"IsAmbiguous":false,"IsVote":true,"OutstackConditionIds":[]}]},{"Id":7,"ManifestationId":793,"Undervotes":0,"Overvotes":0,"OutstackConditionIds":[14],"Marks":[{"CandidateId":552,"ManifestationId":6166,"PartyId":7,"Rank":1,"MarkDensity":100,"IsAmbiguous":false,"IsVote":true,"OutstackConditionIds":[]}]},{"Id":64,"ManifestationId":794,"Undervotes":0,"Overvotes":0,"OutstackConditionIds":[14],"Marks":[{"CandidateId":456,"ManifestationId":6191,"PartyId":1,"Rank":1,"MarkDensity":100,"IsAmbiguous":false,"IsVote":true,"OutstackConditionIds":[]}]},{"Id":68,"ManifestationId":795,"Undervotes":0,"Overvotes":0,"OutstackConditionIds":[],"Marks":[{"CandidateId":218,"ManifestationId":6200,"PartyId":0,"Rank":1,"MarkDensity":100,"IsAmbiguous":false,"IsVote":true,"OutstackConditionIds":[]}]},{"Id":69,"ManifestationId":796,"Undervotes":0,"Overvotes":0,"OutstackConditionIds":[],"Marks":[{"CandidateId":219,"ManifestationId":6201,"PartyId":0,"Rank":1,"MarkDensity":100,"IsAmbiguous":false,"IsVote":true,"OutstackConditionIds":[]}]},{"Id":71,"ManifestationId":797,"Undervotes":0,"Overvotes":0,"OutstackConditionIds":[],"Marks":[{"CandidateId":224,"ManifestationId":6204,"PartyId":0,"Rank":1,"MarkDensity":100,"IsAmbiguous":false,"IsVote":true,"OutstackConditionIds":[]}]},{"Id":72,"ManifestationId":798,"Undervotes":0,"Overvotes":0,"OutstackConditionIds":[],"Marks":[{"CandidateId":226,"ManifestationId":6206,"PartyId":0,"Rank":1,"MarkDensity":100,"IsAmbiguous":false,"IsVote":true,"OutstackConditionIds":[]}]},{"Id":76,"ManifestationId":799,"Undervotes":0,"Overvotes":0,"OutstackConditionIds":[],"Marks":[{"CandidateId":233,"ManifestationId":6207,"PartyId":0,"Rank":1,"MarkDensity":100,"IsAmbiguous":false,"IsVote":true,"OutstackConditionIds":[]}]},{"Id":77,"ManifestationId":800,"Undervotes":0,"Overvotes":0,"OutstackConditionIds":[],"Marks":[{"CandidateId":235,"ManifestationId":6209,"PartyId":0,"Rank":1,"MarkDensity":100,"IsAmbiguous":false,"IsVote":true,"OutstackConditionIds":[]}]},{"Id":129,"ManifestationId":801,"Undervotes":0,"Overvotes":0,"OutstackConditionIds":[],"Marks":[{"CandidateId":340,"ManifestationId":6212,"PartyId":0,"Rank":1,"MarkDensity":100,"IsAmbiguous":false,"IsVote":true,"OutstackConditionIds":[]}]},{"Id":137,"ManifestationId":802,"Undervotes":0,"Overvotes":0,"OutstackConditionIds":[],"Marks":[{"CandidateId":356,"ManifestationId":6214,"PartyId":0,"Rank":1,"MarkDensity":100,"IsAmbiguous":false,"IsVote":true,"OutstackConditionIds":[]}]},{"Id":138,"ManifestationId":803,"Undervotes":0,"Overvotes":0,"OutstackConditionIds":[],"Marks":[{"CandidateId":357,"ManifestationId":6215,"PartyId":0,"Rank":1,"MarkDensity":100,"IsAmbiguous":false,"IsVote":true,"OutstackConditionIds":[]}]}],"OutstackConditionIds":[]}]}},{"TabulatorId":937709,"BatchId":1,"RecordId":4989520,"CountingGroupId":1,"ImageMask":"D:\\NAS\\2024 General Election\\Results\\Tabulator937709\\Batch001\\Images\\937709_00001_4989520*.*","SessionType":"DreVote","VotingSessionIdentifier":"937709_aee4959d-771f-4188-8d13-c1f711ca0558","UniqueVotingIdentifier":"937_1ef1c2f3-9d10-4f99-822f-a4d83878749a","Original":{"PrecinctPortionId":299,"BallotTypeId":41,"IsCurrent":true,"Cards":[{"Id":1053,"KeyInId":1053,"PaperIndex":0,"Contests":[{"Id":4,"ManifestationId":792,"Undervotes":0,"Overvotes":0,"OutstackConditionIds":[14],"Marks":[{"CandidateId":542,"ManifestationId":6105,"PartyId":7,"Rank":1,"MarkDensity":100,"IsAmbiguous":false,"IsVote":true,"OutstackConditionIds":[]}]},{"Id":7,"ManifestationId":793,"Undervotes":0,"Overvotes":0,"OutstackConditionIds":[14],"Marks":[{"CandidateId":520,"ManifestationId":6167,"PartyId":3,"Rank":1,"MarkDensity":100,"IsAmbiguous":false,"IsVote":true,"OutstackConditionIds":[]}]},{"Id":64,"ManifestationId":794,"Undervotes":0,"Overvotes":0,"OutstackConditionIds":[14],"Marks":[{"CandidateId":456,"ManifestationId":6191,"PartyId":1,"Rank":1,"MarkDensity":100,"IsAmbiguous":false,"IsVote":true,"OutstackConditionIds":[]}]},{"Id":68,"ManifestationId":795,"Undervotes":0,"Overvotes":0,"OutstackConditionIds":[],"Marks":[{"CandidateId":217,"ManifestationId":6199,"PartyId":0,"Rank":1,"MarkDensity":100,"IsAmbiguous":false,"IsVote":true,"OutstackConditionIds":[]}]},{"Id":69,"ManifestationId":796,"Undervotes":0,"Overvotes":0,"OutstackConditionIds":[],"Marks":[{"CandidateId":220,"ManifestationId":6202,"PartyId":0,"Rank":1,"MarkDensity":100,"IsAmbiguous":false,"IsVote":true,"OutstackConditionIds":[]}]},{"Id":71,"ManifestationId":797,"Undervotes":0,"Overvotes":0,"OutstackConditionIds":[],"Marks":[{"CandidateId":224,"ManifestationId":6204,"PartyId":0,"Rank":1,"MarkDensity":100,"IsAmbiguous":false,"IsVote":true,"OutstackConditionIds":[]}]},{"Id":72,"ManifestationId":798,"Undervotes":0,"Overvotes":0,"OutstackConditionIds":[],"Marks":[{"CandidateId":226,"ManifestationId":6206,"PartyId":0,"Rank":1,"MarkDensity":100,"IsAmbiguous":false,"IsVote":true,"OutstackConditionIds":[]}]},{"Id":76,"ManifestationId":799,"Undervotes":0,"Overvotes":0,"OutstackConditionIds":[],"Marks":[{"CandidateId":234,"ManifestationId":6208,"PartyId":0,"Rank":1,"MarkDensity":100,"IsAmbiguous":false,"IsVote":true,"OutstackConditionIds":[]}]},{"Id":77,"ManifestationId":800,"Undervotes":0,"Overvotes":0,"OutstackConditionIds":[],"Marks":[{"CandidateId":236,"ManifestationId":6210,"PartyId":0,"Rank":1,"MarkDensity":100,"IsAmbiguous":false,"IsVote":true,"OutstackConditionIds":[]}]},{"Id":129,"ManifestationId":801,"Undervotes":0,"Overvotes":0,"OutstackConditionIds":[],"Marks":[{"CandidateId":340,"ManifestationId":6212,"PartyId":0,"Rank":1,"MarkDensity":100,"IsAmbiguous":false,"IsVote":true,"OutstackConditionIds":[]}]},{"Id":137,"ManifestationId":802,"Undervotes":0,"Overvotes":0,"OutstackConditionIds":[],"Marks":[{"CandidateId":356,"ManifestationId":6214,"PartyId":0,"Rank":1,"MarkDensity":100,"IsAmbiguous":false,"IsVote":true,"OutstackConditionIds":[]}]},{"Id":138,"ManifestationId":803,"Undervotes":0,"Overvotes":0,"OutstackConditionIds":[],"Marks":[{"CandidateId":358,"ManifestationId":6216,"PartyId":0,"Rank":1,"MarkDensity":100,"IsAmbiguous":false,"IsVote":true,"OutstackConditionIds":[]}]}],"OutstackConditionIds":[]}]}}]}